main.py
models/__init__.py
models/frequency.py
models/playback.py
models/track.py
services/__init__.py
services/audio_player.py
services/music_library.py
styles/.gitkeep
styles/app.tcss
views/__init__.py
views/library.py
views/meters.py
views/now_playing.py
widgets/__init__.py
widgets/header.py
sigplay-0.0.2.dist-info/METADATA
sigplay-0.0.2.dist-info/WHEEL
sigplay-0.0.2.dist-info/entry_points.txt
sigplay-0.0.2.dist-info/RECORD
