Metadata-Version: 2.4
Name: sigplay
Version: 0.0.2
Summary: A retro-modern terminal music player
Requires-Python: >=3.13
Requires-Dist: miniaudio>=1.61
Requires-Dist: mutagen>=1.47.0
Requires-Dist: numpy>=1.26.0
Requires-Dist: textual-dev>=1.8.0
Requires-Dist: textual[syntax]>=6.5.0
